MANIFEST.in
README.md
setup.cfg
setup.py
versioneer.py
pynigma/__init__.py
pynigma/_version.py
pynigma/client.py
pynigma.egg-info/PKG-INFO
pynigma.egg-info/SOURCES.txt
pynigma.egg-info/dependency_links.txt
pynigma.egg-info/requires.txt
pynigma.egg-info/top_level.txt