Metadata-Version: 1.1
Name: pynigma
Version: 0.1.0
Summary: A Python client for the Enigma API.
Home-page: https://github.com/thejunglejane/pynigma
Author: Jane Stewart Adams
Author-email: jane@thejunglejane.com
License: MIT
Download-URL: https://github.com/thejunglejane/pynigma/archive/0.1.0.tar.gz
Platform: UNKNOWN
